eruptr/__init__.py
eruptr/args.py
eruptr/config.py
eruptr/exceptions.py
eruptr/modules.py
eruptr/objects.py
eruptr/commands/__init__.py
eruptr/commands/admin.py
eruptr/commands/convert.py
eruptr/commands/init.py
eruptr/commands/load.py
eruptr/commands/project.py
eruptr/commands/stream.py
eruptr/engines/__init__.py
eruptr/engines/clickhouse.py
eruptr/executors/__init__.py
eruptr/executors/step.py
eruptr/executors/unixpipe.py
eruptr/filters/__init__.py
eruptr/formats/__init__.py
eruptr/formats/clickhouse.py
eruptr/io/__init__.py
eruptr/io/clickhouse.py
eruptr/io/file.py
eruptr/locks/__init__.py
eruptr/locks/filesystem.py
eruptr/macros/__init__.py
eruptr/pipes/__init__.py
eruptr/pipes/clickhouse.py
eruptr/pipes/cmd.py
eruptr/pipes/pack.py
eruptr/pipes/python.py
eruptr/pipes/text.py
eruptr/pipes/unpack.py
eruptr/pipes/xml.py
eruptr/streams/__init__.py
eruptr/tasks/__init__.py
eruptr/tasks/clickhouse.py
eruptr/tasks/cmd.py
eruptr/tasks/file.py
eruptr/tasks/pack.py
eruptr/tasks/python.py
eruptr/tasks/unpack.py
eruptr/utils/__init__.py
eruptr/utils/path.py
eruptr-20.12.3.data/scripts/eruptr
eruptr-20.12.3.dist-info/AUTHORS
eruptr-20.12.3.dist-info/COPYING
eruptr-20.12.3.dist-info/COPYING.EXCEPTION
eruptr-20.12.3.dist-info/LICENSE
eruptr-20.12.3.dist-info/METADATA
eruptr-20.12.3.dist-info/WHEEL
eruptr-20.12.3.dist-info/top_level.txt
eruptr-20.12.3.dist-info/RECORD
