Metadata-Version: 2.1
Name: eruptr
Version: 20.12.3
Summary: Data needs a Makefile.
Home-page: https://github.com/VulknData/eruptr
Author: Jason Godden
Author-email: jason@vulkndata.io
License: gpl-3.0
Download-URL: https://github.com/VulknData/eruptr/archive/v20.12.3-alpha.tar.gz
Keywords: clickhouse
Platform: UNKNOWN
Classifier: Development Status :: 3 - Alpha
Classifier: Environment :: Console
Classifier: Intended Audience :: Developers
Classifier: License :: OSI Approved :: GNU General Public License v3 (GPLv3)
Classifier: Natural Language :: English
Classifier: Operating System :: POSIX :: Linux
Classifier: Programming Language :: Python :: 3
Classifier: Programming Language :: Python :: 3.7
Classifier: Topic :: Database
Classifier: Topic :: Database :: Database Engines/Servers
Classifier: Topic :: Software Development :: Libraries :: Python Modules
Requires-Python: >=3.7
Requires-Dist: chardet (>=3.0.4)
Requires-Dist: idna (>=2.10)
Requires-Dist: Jinja2 (>=2.11.2)
Requires-Dist: Mako (>=1.1.3)
Requires-Dist: MarkupSafe (>=1.1.1)
Requires-Dist: PyYAML (>=5.3.1)
Requires-Dist: requests (>=2.25.0)
Requires-Dist: tabulate (>=0.8.7)
Requires-Dist: urllib3 (>=1.26.2)
